image_static_server/__init__.py
image_static_server/main.py
image_static_server-0.0.1.dist-info/LICENSE
image_static_server-0.0.1.dist-info/METADATA
image_static_server-0.0.1.dist-info/WHEEL
image_static_server-0.0.1.dist-info/entry_points.txt
image_static_server-0.0.1.dist-info/RECORD
